flux_hierarchy/__init__.py
flux_hierarchy/hierarchy.py
flux_hierarchy/results.py
flux_hierarchy/runner.py
flux_hierarchy/utils.py
flux_hierarchy/version.py
flux_hierarchy/worker.py
flux_hierarchy/cli/__init__.py
flux_hierarchy/cli/start.py
flux_hierarchy/cli/throughput.py
flux_hierarchy/cli/view.py
flux_hierarchy/logger/__init__.py
flux_hierarchy/logger/generate.py
flux_hierarchy/logger/logger.py
flux_hierarchy-0.0.13.dist-info/LICENSE
flux_hierarchy-0.0.13.dist-info/METADATA
flux_hierarchy-0.0.13.dist-info/NOTICE
flux_hierarchy-0.0.13.dist-info/WHEEL
flux_hierarchy-0.0.13.dist-info/entry_points.txt
flux_hierarchy-0.0.13.dist-info/top_level.txt
flux_hierarchy-0.0.13.dist-info/RECORD
