Metadata-Version: 2.1
Name: flux-hierarchy
Version: 0.0.13
Summary: Instance tree generation for organization or higher throughput submission
Home-page: https://github.com/converged-computing/flux-hierarchy
Author: Vanessa Sochat
Author-email: vsoch@users.noreply.github.com
Maintainer: Vanessa Sochat
License: LICENSE
Keywords: flux,flux-framework,throughput,tree,instances
Classifier: Intended Audience :: Science/Research
Classifier: Intended Audience :: Developers
Classifier: License :: OSI Approved :: MIT License
Classifier: Programming Language :: C
Classifier: Programming Language :: Python
Classifier: Topic :: Software Development
Classifier: Topic :: Scientific/Engineering
Classifier: Operating System :: Unix
Classifier: Programming Language :: Python
Classifier: Programming Language :: Python :: 3.8
Classifier: Programming Language :: Python :: 3.9
Classifier: Programming Language :: Python :: 3.10
Classifier: Programming Language :: Python :: 3.11
License-File: LICENSE
License-File: NOTICE
Requires-Dist: rich
Provides-Extra: all
Requires-Dist: rich ; extra == 'all'
Requires-Dist: pytest ; extra == 'all'
